cf53/__init__.py
cf53/__main__.py
cf53/console.py
cf53/diff.py
cf53/local.py
cf53/main.py
cf53/reconcile.py
cf53/record.py
cf53/remote.py
cf53-0.1.3.dist-info/METADATA
cf53-0.1.3.dist-info/WHEEL
cf53-0.1.3.dist-info/entry_points.txt
cf53-0.1.3.dist-info/top_level.txt
cf53-0.1.3.dist-info/RECORD
