Metadata-Version: 2.4
Name: cf53
Version: 0.1.3
Summary: Cloudflare DNS client for humans
Requires-Python: >=3.13
Requires-Dist: click>=8.3.1
Requires-Dist: cloudflare>=4.3.1
Requires-Dist: rich>=14.2.0
